ufomerge/__init__.py
ufomerge/__main__.py
ufomerge/_version.py
ufomerge/cli.py
ufomerge/layout.py
ufomerge/scaler.py
ufomerge/utils.py
ufomerge-1.9.6.dist-info/licenses/AUTHORS.txt
ufomerge-1.9.6.dist-info/licenses/LICENSE
ufomerge-1.9.6.dist-info/METADATA
ufomerge-1.9.6.dist-info/WHEEL
ufomerge-1.9.6.dist-info/entry_points.txt
ufomerge-1.9.6.dist-info/top_level.txt
ufomerge-1.9.6.dist-info/RECORD
