Metadata-Version: 2.4
Name: ufomerge
Version: 1.9.6
Summary: Merge together two source fonts in UFO format
Author-email: Simon Cozens <simon@simon-cozens.org>
Classifier: Environment :: Console
Classifier: Topic :: Text Processing :: Fonts
License-File: LICENSE
License-File: AUTHORS.txt
Requires-Dist: fonttools>=4.53.1
Requires-Dist: ufoLib2
Provides-Extra: dev
Requires-Dist: pytest; extra == "dev"
Requires-Dist: black; extra == "dev"
Requires-Dist: fontFeatures; extra == "dev"
Dynamic: license-file
